true_detector/__init__.py
true_detector/abstract.py
true_detector/main.py
true_detector/utils.py
true_detector-0.0.2.dist-info/LICENSE
true_detector-0.0.2.dist-info/METADATA
true_detector-0.0.2.dist-info/WHEEL
true_detector-0.0.2.dist-info/entry_points.txt
true_detector-0.0.2.dist-info/top_level.txt
true_detector-0.0.2.dist-info/RECORD
