Metadata-Version: 2.1
Name: true-detector
Version: 0.0.2
Summary: True detector, which identify dead code
Author-email: Stepan Rasputnyi <rasputny.stepan@gmail.com>
Project-URL: Homepage, https://github.com/BigBlackWolf/true-detector
Project-URL: Bug Tracker, https://github.com/BigBlackWolf/true-detector/issues
Classifier: Programming Language :: Python :: 3
Classifier: Programming Language :: Python :: 3 :: Only
Classifier: License :: OSI Approved :: MIT License
Requires-Python: >=3.10
License-File: LICENSE
Requires-Dist: click >=8.0.0
